tulp/__init__.py
tulp/arguments.py
tulp/cli.py
tulp/config.py
tulp/constants.py
tulp/core.py
tulp/executor.py
tulp/input_handler.py
tulp/logger.py
tulp/output_handler.py
tulp/promptSerializer.py
tulp/response_parser.py
tulp/tulpconfig.py
tulp/version.py
tulp/llms/LlmAnthropic.py
tulp/llms/LlmGemini.py
tulp/llms/LlmGroq.py
tulp/llms/LlmOllama.py
tulp/llms/LlmOpenAI.py
tulp/llms/__init__.py
tulp/prompts/__init__.py
tulp/prompts/filtering.py
tulp/prompts/filtering_program.py
tulp/prompts/program.py
tulp/prompts/request.py
tulp-2.10.0.dist-info/METADATA
tulp-2.10.0.dist-info/WHEEL
tulp-2.10.0.dist-info/entry_points.txt
tulp-2.10.0.dist-info/top_level.txt
tulp-2.10.0.dist-info/RECORD
