Metadata-Version: 2.1
Name: tulp
Version: 2.10.0
Summary: TULP: A command line tool, in the best essence of POSIX tooling, that will help you to process, filter, and create data using AI models.
Home-page: https://github.com/fedenunez/tulp
Author: Federico Nuñez
Author-email: fedenunez@gmail.com
License: GPL-2.0 # Use SPDX identifier if possible, or specify file
Classifier: Programming Language :: Python :: 3
Classifier: Programming Language :: Python :: 3.8
Classifier: Programming Language :: Python :: 3.9
Classifier: Programming Language :: Python :: 3.10
Classifier: Programming Language :: Python :: 3.11
Classifier: License :: OSI Approved :: GNU General Public License v2 (GPLv2)
Classifier: Operating System :: OS Independent
Classifier: Environment :: Console
Classifier: Intended Audience :: Developers
Classifier: Intended Audience :: System Administrators
Classifier: Topic :: Utilities
Classifier: Topic :: Text Processing
Requires-Python: >=3.8
Requires-Dist: anthropic <0.28.0,>=0.25.0
Requires-Dist: google-genai >=1.50.0
Requires-Dist: groq <0.9.0,>=0.5.0
Requires-Dist: ollama >=0.4.0
Requires-Dist: openai <2.0.0,>=1.40.0
